{"version":1,"resource":"file:///home/deltacat/.config/illogical-impulse/config.json","entries":[{"id":"N8xN.json","timestamp":1770274863671},{"id":"UsiP.json","timestamp":1770276898734},{"id":"iMI6.json","timestamp":1770277120496},{"id":"JQKZ.json","timestamp":1770311951185},{"id":"9Vtz.json","timestamp":1770312041661},{"id":"DRb6.json","timestamp":1770312152230},{"id":"WKsV.json","timestamp":1770312181693},{"id":"74P5.json","timestamp":1770312257775},{"id":"XNFl.json","timestamp":1770312356038},{"id":"ucJr.json","timestamp":1770312399414},{"id":"6A4a.json","timestamp":1770312466102},{"id":"05R2.json","timestamp":1770312492290},{"id":"0Nhh.json","timestamp":1770312528148},{"id":"TOyo.json","timestamp":1770312540792},{"id":"z6y8.json","timestamp":1770312839761},{"id":"CKYg.json","timestamp":1770312877990},{"id":"ovWZ.json","timestamp":1770313438736},{"id":"eUaR.json","timestamp":1770313479737},{"id":"1nYw.json","timestamp":1770313934970}]}